{"trial_id": "3", "hyperparameters": {"space": [{"class_name": "Choice", "config": {"name": "seq_length", "default": 5, "conditions": [], "values": [5, 10, 20], "ordered": true}}, {"class_name": "Int", "config": {"name": "num_layers", "default": null, "conditions": [], "min_value": 1, "max_value": 2, "step": 1, "sampling": "linear"}}, {"class_name": "Choice", "config": {"name": "units_0", "default": 16, "conditions": [], "values": [16, 32, 64], "ordered": true}}, {"class_name": "Choice", "config": {"name": "dropout_0", "default": 0.1, "conditions": [], "values": [0.1, 0.2, 0.3], "ordered": true}}, {"class_name": "Choice", "config": {"name": "learning_rate", "default": 0.0001, "conditions": [], "values": [0.0001, 0.001, 0.01], "ordered": true}}, {"class_name": "Choice", "config": {"name": "units_1", "default": 16, "conditions": [], "values": [16, 32, 64], "ordered": true}}, {"class_name": "Choice", "config": {"name": "dropout_1", "default": 0.1, "conditions": [], "values": [0.1, 0.2, 0.3], "ordered": true}}], "values": {"seq_length": 5, "num_layers": 1, "units_0": 16, "dropout_0": 0.3, "learning_rate": 0.01, "units_1": 64, "dropout_1": 0.1}}, "metrics": {"metrics": {"loss": {"direction": "min", "observations": [{"value": [0.0029870596481487155], "step": 10}]}, "mean_absolute_error": {"direction": "min", "observations": [{"value": [0.03753127343952656], "step": 10}]}, "mean_absolute_percentage_error": {"direction": "min", "observations": [{"value": [14870.1767578125], "step": 10}]}, "val_loss": {"direction": "min", "observations": [{"value": [5.4287085731630214e-05], "step": 10}]}, "val_mean_absolute_error": {"direction": "min", "observations": [{"value": [0.005611563567072153], "step": 10}]}, "val_mean_absolute_percentage_error": {"direction": "min", "observations": [{"value": [2.419674277305603], "step": 10}]}}}, "score": 5.4287085731630214e-05, "best_step": 10, "status": "COMPLETED", "message": null}